peregrine/__init__.py
peregrine/apps.py
peregrine/models.py
peregrine/urls.py
peregrine/views.py
peregrine/wagtail_hooks.py
peregrine/fixtures/initial_site.json
peregrine/management/commands/peregrine_initial_site.py
peregrine/migrations/0001_initial.py
peregrine/migrations/0002_auto_20171216_1408.py
peregrine/migrations/0003_auto_20171217_1706.py
peregrine/migrations/0004_auto_20180105_1315.py
peregrine/migrations/0005_auto_20180418_1637.py
peregrine/migrations/0006_auto_20180418_1652.py
peregrine/migrations/0007_auto_20180523_1908.py
peregrine/migrations/0008_peregrinesettings_revisions_to_keep.py
peregrine/migrations/0009_auto_20211105_1634.py
peregrine/migrations/__init__.py
peregrine/static/peregrine/peregrine-style.css
peregrine/static/peregrine/peregrine-style.min.css
peregrine/static/peregrine/peregrine-style.min.css.gz
peregrine/templates/peregrine/__init__.py
peregrine/templates/peregrine/base.html
peregrine/templates/peregrine/site_page.html
peregrine/templates/peregrine/site_post.html
peregrine/templates/peregrine/site_post_list.html
peregrine/templates/peregrine/tags/top_menu.html
peregrine/templates/peregrine/tags/top_menu_children.html
peregrine/templates/peregrine/tags/top_menu_posts.html
peregrine/templates/wagtailcontentstream/blocks/captioned_image.html
peregrine/templates/wagtailcontentstream/blocks/heading.html
peregrine/templates/wagtailembeds/embed_frontend.html
peregrine/templatetags/__init__.py
peregrine/templatetags/peregrine.py
peregrine-0.5.1.dist-info/LICENSE
peregrine-0.5.1.dist-info/METADATA
peregrine-0.5.1.dist-info/WHEEL
peregrine-0.5.1.dist-info/top_level.txt
peregrine-0.5.1.dist-info/RECORD
