Metadata-Version: 2.1
Name: peregrine
Version: 0.5.1
Summary: Peregrine is an opinioned blog system for the Wagtail content management system on the Django Web Framework.
Home-page: https://github.com/FlipperPA/peregrine
Author: Tim Allen
Author-email: tallen@wharton.upenn.edu
Classifier: Development Status :: 3 - Alpha
Classifier: Environment :: Web Environment
Classifier: Intended Audience :: Developers
Classifier: License :: OSI Approved :: BSD License
Classifier: Operating System :: OS Independent
Classifier: Programming Language :: Python :: 3
Classifier: Programming Language :: Python :: 3.6
Classifier: Programming Language :: Python :: 3.7
Classifier: Programming Language :: Python :: 3.8
Classifier: Programming Language :: Python :: 3.9
Classifier: Programming Language :: Python :: 3 :: Only
Classifier: Framework :: Django
Classifier: Framework :: Django :: 2.2
Classifier: Framework :: Django :: 3.0
Classifier: Framework :: Django :: 3.1
Classifier: Framework :: Django :: 3.2
Classifier: Framework :: Django :: 4.0
Classifier: Framework :: Wagtail
Classifier: Framework :: Wagtail :: 2
Classifier: Topic :: Internet :: WWW/HTTP
Classifier: Topic :: Internet :: WWW/HTTP :: Dynamic Content
License-File: LICENSE
Requires-Dist: wagtail (<3.0,>=2.15)
Requires-Dist: wagtailcontentstream (>=0.4.0)
Requires-Dist: wagtailcodeblock (<=1.28.0django-bootstrap4>=2)
